getfilenuitkapython/README.md
getfilenuitkapython/__init__.py
getfilenuitkapython/requirements.txt
getfilenuitkapython/thirdparty.json
getfilenuitkapython-0.11.dist-info/LICENSE.rst
getfilenuitkapython-0.11.dist-info/METADATA
getfilenuitkapython-0.11.dist-info/WHEEL
getfilenuitkapython-0.11.dist-info/top_level.txt
getfilenuitkapython-0.11.dist-info/RECORD
