Metadata-Version: 2.1
Name: getfilenuitkapython
Version: 0.11
Summary: A function that locates files in python environments and compiled exe files (Nuitka)
Home-page: https://github.com/hansalemaos/getfilenuitkapython
Author: Johannes Fischer
Author-email: aulasparticularesdealemaosp@gmail.com
License: MIT
Keywords: nuitka,locate,files
Classifier: Development Status :: 4 - Beta
Classifier: Programming Language :: Python :: 3 :: Only
Classifier: Programming Language :: Python :: 3.10
Classifier: Topic :: Software Development :: Libraries :: Python Modules
Classifier: Topic :: Utilities
License-File: LICENSE.rst
Requires-Dist: list-all-files-recursively
Requires-Dist: shlexwhichplus
